fragment/__init__.py
fragment/client/__init__.py
fragment/client/async_client.py
fragment/client/sync_client.py
fragment/codegen/__init__.py
fragment/codegen/helpers.py
fragment/codegen/main.py
fragment/codegen/plugins/__init__.py
fragment/codegen/plugins/generate_client_method.py
fragment/codegen/plugins/get_file_comment.py
fragment/exceptions.py
fragment/logger.py
fragment/sdk/__init__.py
fragment/sdk/add_ledger_entry.py
fragment/sdk/add_ledger_entry_runtime.py
fragment/sdk/async_client.py
fragment/sdk/base_model.py
fragment/sdk/client.py
fragment/sdk/create_custom_currency.py
fragment/sdk/create_custom_link.py
fragment/sdk/create_ledger.py
fragment/sdk/delete_custom_txs.py
fragment/sdk/delete_ledger.py
fragment/sdk/delete_schema.py
fragment/sdk/enums.py
fragment/sdk/get_account_data_migrations.py
fragment/sdk/get_entries_to_migrate_for_ledger_account_data_migration.py
fragment/sdk/get_entries_to_migrate_for_ledger_entry_data_migration.py
fragment/sdk/get_entry_data_migrations.py
fragment/sdk/get_ledger.py
fragment/sdk/get_ledger_account_balance.py
fragment/sdk/get_ledger_account_balance_with_child_rollup.py
fragment/sdk/get_ledger_account_lines.py
fragment/sdk/get_ledger_entry.py
fragment/sdk/get_schema.py
fragment/sdk/get_workspace.py
fragment/sdk/input_types.py
fragment/sdk/list_ledger_account_balances.py
fragment/sdk/list_ledger_accounts.py
fragment/sdk/list_ledger_entries.py
fragment/sdk/list_ledger_entry_group_balances.py
fragment/sdk/list_multi_currency_ledger_account_balances.py
fragment/sdk/migrate_ledger_entry.py
fragment/sdk/reconcile_tx.py
fragment/sdk/reconcile_tx_runtime.py
fragment/sdk/reverse_ledger_entry.py
fragment/sdk/store_schema.py
fragment/sdk/sync_custom_accounts.py
fragment/sdk/sync_custom_txs.py
fragment/sdk/update_ledger.py
fragment/sdk/update_ledger_entry.py
fragment/std_queries/queries.graphql
fragment/sync_sdk/__init__.py
fragment/sync_sdk/add_ledger_entry.py
fragment/sync_sdk/add_ledger_entry_runtime.py
fragment_python-0.5.2.dist-info/LICENSE
fragment_python-0.5.2.dist-info/METADATA
fragment_python-0.5.2.dist-info/WHEEL
fragment_python-0.5.2.dist-info/entry_points.txt
fragment_python-0.5.2.dist-info/RECORD
