Metadata-Version: 2.3
Name: fragment-python
Version: 0.5.2
Summary: Python SDK for https://fragment.dev/
License: Apache 2.0
Author: Fragment Foundries Inc
Requires-Python: >=3.10,<4.0
Classifier: License :: Other/Proprietary License
Classifier: Programming Language :: Python :: 3
Classifier: Programming Language :: Python :: 3.10
Classifier: Programming Language :: Python :: 3.11
Classifier: Programming Language :: Python :: 3.12
Classifier: Programming Language :: Python :: 3.13
Requires-Dist: ariadne-codegen (>=0.13.0,<0.14.0)
Requires-Dist: authlib (>=1.3.1,<2.0.0)
Requires-Dist: certifi (==2024.07.04)
Requires-Dist: click (>=8.1.7,<9.0.0)
Requires-Dist: cryptography (==44.0.1)
Requires-Dist: graphql-core (>=3.2.3,<4.0.0)
Requires-Dist: httpx (>=0.28.1,<0.29.0)
Requires-Dist: pydantic (>=2.8.0,<3.0.0)
Requires-Dist: requests-oauth2client (>=1.6.0,<2.0.0)
